Classfile /home/jonathan/workspace/CodeAPI/src/test/resources/AnnotatedTest_AnnotatedTestClass_Result.class
  Last modified 06/12/2016; size 843 bytes
  MD5 checksum 57110033bfc5b90bc47e09e41e09d20c
  Compiled from "AnnotatedTestClass.cai"
public class test.AnnotatedTestClass
  minor version: 0
  major version: 52
  flags: ACC_PUBLIC, ACC_SUPER
Constant pool:
   #1 = Utf8               AnnotatedTestClass.cai
   #2 = Utf8               test/AnnotatedTestClass
   #3 = Class              #2             // test/AnnotatedTestClass
   #4 = Utf8               java/lang/Object
   #5 = Class              #4             // java/lang/Object
   #6 = Utf8               Lcom/github/jonathanxd/codeapi/test/AnnotatedTest_$Simple;
   #7 = Utf8               value
   #8 = Utf8               Lcom/github/jonathanxd/codeapi/test/AnnotatedTest_$MyEnum;
   #9 = Utf8               A
  #10 = Utf8               B
  #11 = Utf8               C
  #12 = Utf8               polymorphic
  #13 = Utf8               (Ljava/lang/Object;)Ljava/lang/Object;
  #14 = Utf8               Ljava/lang/invoke/MethodHandle/PolymorphicSignature;
  #15 = Utf8               Ljava/lang/Deprecated;
  #16 = Utf8               first
  #17 = Utf8               Ljava/lang/Object;
  #18 = Utf8               field
  #19 = Utf8               Ljava/lang/String;
  #20 = Utf8               <init>
  #21 = Utf8               ()V
  #22 = NameAndType        #20:#21        // "<init>":()V
  #23 = Methodref          #5.#22         // java/lang/Object."<init>":()V
  #24 = Utf8               this
  #25 = Utf8               Ltest/AnnotatedTestClass;
  #26 = Utf8               <clinit>
  #27 = NameAndType        #18:#19        // field:Ljava/lang/String;
  #28 = Fieldref           #3.#27         // test/AnnotatedTestClass.field:Ljava/lang/String;
  #29 = Utf8               RuntimeVisibleAnnotations
  #30 = Utf8               Code
  #31 = Utf8               LocalVariableTable
  #32 = Utf8               RuntimeVisibleParameterAnnotations
  #33 = Utf8               SourceFile
{
  public static java.lang.String field;
    descriptor: Ljava/lang/String;
    flags: ACC_PUBLIC, ACC_STATIC
    RuntimeVisibleAnnotations:
      0: #6(#7=[e#8.#9])

  public static java.lang.Object polymorphic(java.lang.Object);
    descriptor: (Ljava/lang/Object;)Ljava/lang/Object;
    flags: ACC_PUBLIC, ACC_STATIC
    Code:
      stack=1, locals=1, args_size=1
         0: aconst_null
         1: areturn
      LocalVariableTable:
        Start  Length  Slot  Name   Signature
            0       2     0 first   Ljava/lang/Object;
    RuntimeVisibleAnnotations:
      0: #14()
    RuntimeVisibleParameterAnnotations:
      parameter 0:
        0: #15()

  public test.AnnotatedTestClass();
    descriptor: ()V
    flags: ACC_PUBLIC
    Code:
      stack=1, locals=1, args_size=1
         0: aload_0
         1: invokespecial #23                 // Method java/lang/Object."<init>":()V
         4: return
      LocalVariableTable:
        Start  Length  Slot  Name   Signature
            0       5     0  this   Ltest/AnnotatedTestClass;

  static {};
    descriptor: ()V
    flags: ACC_STATIC
    Code:
      stack=1, locals=0, args_size=0
         0: aconst_null
         1: putstatic     #28                 // Field field:Ljava/lang/String;
         4: return
}
SourceFile: "AnnotatedTestClass.cai"
RuntimeVisibleAnnotations:
  0: #6(#7=[e#8.#9,e#8.#10,e#8.#11])
