Classfile /home/jonathan/workspace/CodeAPI/src/test/resources/ArrayTest_Result.class
  Last modified 06/12/2016; size 900 bytes
  MD5 checksum 025a9dbec4dc6be5d79da3963b0c1969
  Compiled from "CommonGen_Generated.cai"
public class com.github.jonathanxd.codeapi.test.CommonGen_Generated
  minor version: 0
  major version: 52
  flags: ACC_PUBLIC, ACC_SUPER
Constant pool:
   #1 = Utf8               CommonGen_Generated.cai
   #2 = Utf8               com/github/jonathanxd/codeapi/test/CommonGen_Generated
   #3 = Class              #2             // com/github/jonathanxd/codeapi/test/CommonGen_Generated
   #4 = Utf8               java/lang/Object
   #5 = Class              #4             // java/lang/Object
   #6 = Utf8               <init>
   #7 = Utf8               ()V
   #8 = NameAndType        #6:#7          // "<init>":()V
   #9 = Methodref          #5.#8          // java/lang/Object."<init>":()V
  #10 = Utf8               [Ljava/lang/String;
  #11 = Class              #10            // "[Ljava/lang/String;"
  #12 = Utf8               java/lang/String
  #13 = Class              #12            // java/lang/String
  #14 = Utf8               A
  #15 = String             #14            // A
  #16 = Utf8               B
  #17 = String             #16            // B
  #18 = Utf8               C
  #19 = String             #18            // C
  #20 = Utf8               D
  #21 = String             #20            // D
  #22 = Utf8               E
  #23 = String             #22            // E
  #24 = Utf8               F
  #25 = String             #24            // F
  #26 = Utf8               G
  #27 = String             #26            // G
  #28 = Utf8               H
  #29 = String             #28            // H
  #30 = Utf8               I
  #31 = String             #30            // I
  #32 = Utf8               J
  #33 = String             #32            // J
  #34 = Utf8               java/lang/Integer
  #35 = Class              #34            // java/lang/Integer
  #36 = Utf8               (I)V
  #37 = NameAndType        #6:#36         // "<init>":(I)V
  #38 = Methodref          #35.#37        // java/lang/Integer."<init>":(I)V
  #39 = Utf8               java/lang/System
  #40 = Class              #39            // java/lang/System
  #41 = Utf8               out
  #42 = Utf8               Ljava/io/PrintStream;
  #43 = NameAndType        #41:#42        // out:Ljava/io/PrintStream;
  #44 = Fieldref           #40.#43        // java/lang/System.out:Ljava/io/PrintStream;
  #45 = Utf8               java/io/PrintStream
  #46 = Class              #45            // java/io/PrintStream
  #47 = Utf8               println
  #48 = Utf8               (Ljava/lang/String;)V
  #49 = NameAndType        #47:#48        // println:(Ljava/lang/String;)V
  #50 = Methodref          #46.#49        // java/io/PrintStream.println:(Ljava/lang/String;)V
  #51 = Utf8               this
  #52 = Utf8               Lcom/github/jonathanxd/codeapi/test/CommonGen_Generated;
  #53 = Utf8               array
  #54 = Utf8               [[Ljava/lang/String;
  #55 = Utf8               array2
  #56 = Utf8               array3
  #57 = Utf8               [Ljava/lang/Object;
  #58 = Utf8               <clinit>
  #59 = Utf8               Code
  #60 = Utf8               LocalVariableTable
  #61 = Utf8               SourceFile
{
  public com.github.jonathanxd.codeapi.test.CommonGen_Generated();
    descriptor: ()V
    flags: ACC_PUBLIC
    Code:
      stack=7, locals=4, args_size=1
         0: aload_0
         1: invokespecial #9                  // Method java/lang/Object."<init>":()V
         4: iconst_2
         5: anewarray     #11                 // class "[Ljava/lang/String;"
         8: dup
         9: iconst_0
        10: iconst_5
        11: anewarray     #13                 // class java/lang/String
        14: dup
        15: iconst_0
        16: ldc           #15                 // String A
        18: aastore
        19: dup
        20: iconst_1
        21: ldc           #17                 // String B
        23: aastore
        24: dup
        25: iconst_2
        26: ldc           #19                 // String C
        28: aastore
        29: dup
        30: iconst_3
        31: ldc           #21                 // String D
        33: aastore
        34: dup
        35: iconst_4
        36: ldc           #23                 // String E
        38: aastore
        39: aastore
        40: dup
        41: iconst_1
        42: iconst_5
        43: anewarray     #13                 // class java/lang/String
        46: dup
        47: iconst_0
        48: ldc           #25                 // String F
        50: aastore
        51: dup
        52: iconst_1
        53: ldc           #27                 // String G
        55: aastore
        56: dup
        57: iconst_2
        58: ldc           #29                 // String H
        60: aastore
        61: dup
        62: iconst_3
        63: ldc           #31                 // String I
        65: aastore
        66: dup
        67: iconst_4
        68: ldc           #33                 // String J
        70: aastore
        71: aastore
        72: astore_1
        73: iconst_0
        74: anewarray     #11                 // class "[Ljava/lang/String;"
        77: astore_2
        78: iconst_1
        79: anewarray     #5                  // class java/lang/Object
        82: dup
        83: iconst_0
        84: new           #35                 // class java/lang/Integer
        87: dup
        88: iconst_1
        89: invokespecial #38                 // Method java/lang/Integer."<init>":(I)V
        92: checkcast     #5                  // class java/lang/Object
        95: aastore
        96: astore_3
        97: getstatic     #44                 // Field java/lang/System.out:Ljava/io/PrintStream;
       100: aload_1
       101: iconst_0
       102: aaload
       103: iconst_0
       104: aaload
       105: invokevirtual #50                 // Method java/io/PrintStream.println:(Ljava/lang/String;)V
       108: return
      LocalVariableTable:
        Start  Length  Slot  Name   Signature
            0     109     0  this   Lcom/github/jonathanxd/codeapi/test/CommonGen_Generated;
           72      37     1 array   [[Ljava/lang/String;
           77      32     2 array2   [Ljava/lang/String;
           96      13     3 array3   [Ljava/lang/Object;

  static {};
    descriptor: ()V
    flags: ACC_STATIC
    Code:
      stack=0, locals=0, args_size=0
         0: return
}
SourceFile: "CommonGen_Generated.cai"
