Classfile /home/jonathan/workspace/CodeAPI/src/test/resources/BridgeMethodsTest_Result.class
  Last modified 17/11/2016; size 1235 bytes
  MD5 checksum 51fa450dbe30193f0bdd670ec2f2d0f8
  Compiled from "bridgeTest.cai"
public class com.bridgeTest extends java.lang.Object implements com.AB<java.util.List>
  minor version: 0
  major version: 52
  flags: ACC_PUBLIC, ACC_SUPER
Constant pool:
   #1 = Utf8               bridgeTest.cai
   #2 = Utf8               com/bridgeTest
   #3 = Class              #2             // com/bridgeTest
   #4 = Utf8               Ljava/lang/Object;Lcom/AB<Ljava/util/List;>;
   #5 = Utf8               java/lang/Object
   #6 = Class              #5             // java/lang/Object
   #7 = Utf8               com/AB
   #8 = Class              #7             // com/AB
   #9 = Utf8               iterate
  #10 = Utf8               (Ljava/lang/Iterable;)V
  #11 = Utf8               java/util/List
  #12 = Class              #11            // java/util/List
  #13 = Utf8               (Ljava/util/List;)V
  #14 = NameAndType        #9:#13         // iterate:(Ljava/util/List;)V
  #15 = Methodref          #3.#14         // com/bridgeTest.iterate:(Ljava/util/List;)V
  #16 = Utf8               this
  #17 = Utf8               Lcom/bridgeTest;
  #18 = Utf8               iter
  #19 = Utf8               Ljava/lang/Iterable<T*;>;
  #20 = Utf8               Ljava/lang/Iterable;
  #21 = Utf8               get
  #22 = Utf8               (I)Ljava/lang/Object;
  #23 = NameAndType        #21:#22        // get:(I)Ljava/lang/Object;
  #24 = InterfaceMethodref #12.#23        // java/util/List.get:(I)Ljava/lang/Object;
  #25 = Utf8               java/lang/Iterable
  #26 = Class              #25            // java/lang/Iterable
  #27 = Utf8               iterator
  #28 = Utf8               ()Ljava/util/Iterator;
  #29 = NameAndType        #27:#28        // iterator:()Ljava/util/Iterator;
  #30 = InterfaceMethodref #26.#29        // java/lang/Iterable.iterator:()Ljava/util/Iterator;
  #31 = Utf8               java/util/Iterator
  #32 = Class              #31            // java/util/Iterator
  #33 = Utf8               hasNext
  #34 = Utf8               ()Z
  #35 = NameAndType        #33:#34        // hasNext:()Z
  #36 = InterfaceMethodref #32.#35        // java/util/Iterator.hasNext:()Z
  #37 = Utf8               next
  #38 = Utf8               ()Ljava/lang/Object;
  #39 = NameAndType        #37:#38        // next:()Ljava/lang/Object;
  #40 = InterfaceMethodref #32.#39        // java/util/Iterator.next:()Ljava/lang/Object;
  #41 = Utf8               java/lang/System
  #42 = Class              #41            // java/lang/System
  #43 = Utf8               out
  #44 = Utf8               Ljava/io/PrintStream;
  #45 = NameAndType        #43:#44        // out:Ljava/io/PrintStream;
  #46 = Fieldref           #42.#45        // java/lang/System.out:Ljava/io/PrintStream;
  #47 = Utf8               toString
  #48 = Utf8               ()Ljava/lang/String;
  #49 = NameAndType        #47:#48        // toString:()Ljava/lang/String;
  #50 = Methodref          #6.#49         // java/lang/Object.toString:()Ljava/lang/String;
  #51 = Utf8               java/io/PrintStream
  #52 = Class              #51            // java/io/PrintStream
  #53 = Utf8               println
  #54 = Utf8               (Ljava/lang/String;)V
  #55 = NameAndType        #53:#54        // println:(Ljava/lang/String;)V
  #56 = Methodref          #52.#55        // java/io/PrintStream.println:(Ljava/lang/String;)V
  #57 = Utf8               Ljava/util/List;
  #58 = Utf8               obj
  #59 = Utf8               Ljava/lang/Object;
  #60 = Utf8               <init>
  #61 = Utf8               ()V
  #62 = NameAndType        #60:#61        // "<init>":()V
  #63 = Methodref          #6.#62         // java/lang/Object."<init>":()V
  #64 = Utf8               <clinit>
  #65 = Utf8               Code
  #66 = Utf8               LocalVariableTable
  #67 = Utf8               LocalVariableTypeTable
  #68 = Utf8               Signature
  #69 = Utf8               (Ljava/lang/Iterable<T*;>;)V
  #70 = Utf8               StackMapTable
  #71 = Utf8               SourceFile
{
  public void iterate(java.lang.Iterable<*>);
    descriptor: (Ljava/lang/Iterable;)V
    flags: ACC_PUBLIC, ACC_BRIDGE
    Code:
      stack=2, locals=2, args_size=2
         0: aload_0
         1: aload_1
         2: checkcast     #12                 // class java/util/List
         5: invokevirtual #15                 // Method iterate:(Ljava/util/List;)V
         8: return
      LocalVariableTable:
        Start  Length  Slot  Name   Signature
            0       9     0  this   Lcom/bridgeTest;
            0       9     1  iter   Ljava/lang/Iterable;
      LocalVariableTypeTable:
        Start  Length  Slot  Name   Signature
            0       9     1  iter   Ljava/lang/Iterable<T*;>;
    Signature: #69                          // (Ljava/lang/Iterable<T*;>;)V

  public void iterate(java.util.List);
    descriptor: (Ljava/util/List;)V
    flags: ACC_PUBLIC
    Code:
      stack=3, locals=4, args_size=2
         0: aload_1
         1: iconst_0
         2: invokeinterface #24,  2           // InterfaceMethod java/util/List.get:(I)Ljava/lang/Object;
         7: aload_1
         8: invokeinterface #30,  1           // InterfaceMethod java/lang/Iterable.iterator:()Ljava/util/Iterator;
        13: astore_2
        14: aload_2
        15: invokeinterface #36,  1           // InterfaceMethod java/util/Iterator.hasNext:()Z
        20: ifeq          43
        23: aload_2
        24: invokeinterface #40,  1           // InterfaceMethod java/util/Iterator.next:()Ljava/lang/Object;
        29: astore_3
        30: getstatic     #46                 // Field java/lang/System.out:Ljava/io/PrintStream;
        33: aload_3
        34: invokevirtual #50                 // Method java/lang/Object.toString:()Ljava/lang/String;
        37: invokevirtual #56                 // Method java/io/PrintStream.println:(Ljava/lang/String;)V
        40: goto          14
        43: return
      LocalVariableTable:
        Start  Length  Slot  Name   Signature
            0      44     0  this   Lcom/bridgeTest;
            0      44     1  iter   Ljava/util/List;
           29      15     3   obj   Ljava/lang/Object;
      StackMapTable: number_of_entries = 2
        frame_type = 255 /* full_frame */
          offset_delta = 14
          locals = [ class com/bridgeTest, class java/util/List, class java/util/Iterator ]
          stack = [ class java/lang/Object ]
        frame_type = 92 /* same_locals_1_stack_item */
          stack = [ class java/lang/Object ]

  public com.bridgeTest();
    descriptor: ()V
    flags: ACC_PUBLIC
    Code:
      stack=1, locals=1, args_size=1
         0: aload_0
         1: invokespecial #63                 // Method java/lang/Object."<init>":()V
         4: return
      LocalVariableTable:
        Start  Length  Slot  Name   Signature
            0       5     0  this   Lcom/bridgeTest;

  static {};
    descriptor: ()V
    flags: ACC_STATIC
    Code:
      stack=0, locals=0, args_size=0
         0: return
}
Signature: #4                           // Ljava/lang/Object;Lcom/AB<Ljava/util/List;>;
SourceFile: "bridgeTest.cai"
