Classfile /home/jonathan/workspace/CodeAPI/src/test/resources/CallMethodFragment_MethodFragment_Result.class
  Last modified 17/11/2016; size 697 bytes
  MD5 checksum f537ac566a1d2b2440c1ac944dcaccc7
  Compiled from "MethodFragment.cai"
public class com.MethodFragment
  minor version: 0
  major version: 52
  flags: ACC_PUBLIC, ACC_SUPER
Constant pool:
   #1 = Utf8               MethodFragment.cai
   #2 = Utf8               com/MethodFragment
   #3 = Class              #2             // com/MethodFragment
   #4 = Utf8               java/lang/Object
   #5 = Class              #4             // java/lang/Object
   #6 = Utf8               test
   #7 = Utf8               ()V
   #8 = Utf8               java/lang/System
   #9 = Class              #8             // java/lang/System
  #10 = Utf8               out
  #11 = Utf8               Ljava/io/PrintStream;
  #12 = NameAndType        #10:#11        // out:Ljava/io/PrintStream;
  #13 = Fieldref           #9.#12         // java/lang/System.out:Ljava/io/PrintStream;
  #14 = Utf8               BOB
  #15 = String             #14            // BOB
  #16 = Utf8               MethodFragment_fragment$1370427547
  #17 = Utf8               (Ljava/lang/String;)Ljava/lang/String;
  #18 = NameAndType        #16:#17        // MethodFragment_fragment$1370427547:(Ljava/lang/String;)Ljava/lang/String;
  #19 = Methodref          #3.#18         // com/MethodFragment.MethodFragment_fragment$1370427547:(Ljava/lang/String;)Ljava/lang/String;
  #20 = Utf8               java/io/PrintStream
  #21 = Class              #20            // java/io/PrintStream
  #22 = Utf8               println
  #23 = Utf8               (Ljava/lang/String;)V
  #24 = NameAndType        #22:#23        // println:(Ljava/lang/String;)V
  #25 = Methodref          #21.#24        // java/io/PrintStream.println:(Ljava/lang/String;)V
  #26 = Utf8               Ljava/lang/Object;
  #27 = Utf8               TT;
  #28 = Utf8               <init>
  #29 = NameAndType        #28:#7         // "<init>":()V
  #30 = Methodref          #5.#29         // java/lang/Object."<init>":()V
  #31 = Utf8               this
  #32 = Utf8               Lcom/MethodFragment;
  #33 = Utf8               input
  #34 = Utf8               Ljava/lang/String;
  #35 = Utf8               <clinit>
  #36 = Utf8               Signature
  #37 = Utf8               Code
  #38 = Utf8               LocalVariableTable
  #39 = Utf8               SourceFile
{
  public T test;
    descriptor: Ljava/lang/Object;
    flags: ACC_PUBLIC
    Signature: #27                          // TT;

  public static void test();
    descriptor: ()V
    flags: ACC_PUBLIC, ACC_STATIC
    Code:
      stack=2, locals=0, args_size=0
         0: getstatic     #13                 // Field java/lang/System.out:Ljava/io/PrintStream;
         3: ldc           #15                 // String BOB
         5: invokestatic  #19                 // Method MethodFragment_fragment$1370427547:(Ljava/lang/String;)Ljava/lang/String;
         8: invokevirtual #25                 // Method java/io/PrintStream.println:(Ljava/lang/String;)V
        11: return

  public com.MethodFragment();
    descriptor: ()V
    flags: ACC_PUBLIC
    Code:
      stack=1, locals=1, args_size=1
         0: aload_0
         1: invokespecial #30                 // Method java/lang/Object."<init>":()V
         4: return
      LocalVariableTable:
        Start  Length  Slot  Name   Signature
            0       5     0  this   Lcom/MethodFragment;

  private static java.lang.String MethodFragment_fragment$1370427547(java.lang.String);
    descriptor: (Ljava/lang/String;)Ljava/lang/String;
    flags: ACC_PRIVATE, ACC_STATIC
    Code:
      stack=1, locals=1, args_size=1
         0: aload_0
         1: areturn
      LocalVariableTable:
        Start  Length  Slot  Name   Signature
            0       2     0 input   Ljava/lang/String;

  static {};
    descriptor: ()V
    flags: ACC_STATIC
    Code:
      stack=0, locals=0, args_size=0
         0: return
}
SourceFile: "MethodFragment.cai"
