Classfile /home/jonathan/workspace/CodeAPI/src/test/resources/CodeAPITest_API_Result.class
  Last modified 18/11/2016; size 645 bytes
  MD5 checksum e2cbaa4a62df9998efb8144812205720
  Compiled from "CodeAPITest_API_Generated.cai"
public class com.github.jonathanxd.codeapi.test.bytecode.CodeAPITest_API_Generated
  minor version: 0
  major version: 52
  flags: ACC_PUBLIC, ACC_SUPER
Constant pool:
   #1 = Utf8               CodeAPITest_API_Generated.cai
   #2 = Utf8               com/github/jonathanxd/codeapi/test/bytecode/CodeAPITest_API_Generated
   #3 = Class              #2             // com/github/jonathanxd/codeapi/test/bytecode/CodeAPITest_API_Generated
   #4 = Utf8               java/lang/Object
   #5 = Class              #4             // java/lang/Object
   #6 = Utf8               printString
   #7 = Utf8               (Ljava/lang/String;)V
   #8 = Utf8               java/lang/System
   #9 = Class              #8             // java/lang/System
  #10 = Utf8               out
  #11 = Utf8               Ljava/io/PrintStream;
  #12 = NameAndType        #10:#11        // out:Ljava/io/PrintStream;
  #13 = Fieldref           #9.#12         // java/lang/System.out:Ljava/io/PrintStream;
  #14 = Utf8               java/io/PrintStream
  #15 = Class              #14            // java/io/PrintStream
  #16 = Utf8               println
  #17 = NameAndType        #16:#7         // println:(Ljava/lang/String;)V
  #18 = Methodref          #15.#17        // java/io/PrintStream.println:(Ljava/lang/String;)V
  #19 = Utf8               string
  #20 = Utf8               Ljava/lang/String;
  #21 = Utf8               <init>
  #22 = Utf8               ()V
  #23 = NameAndType        #21:#22        // "<init>":()V
  #24 = Methodref          #5.#23         // java/lang/Object."<init>":()V
  #25 = Utf8               this
  #26 = Utf8               Lcom/github/jonathanxd/codeapi/test/bytecode/CodeAPITest_API_Generated;
  #27 = Utf8               <clinit>
  #28 = Utf8               Code
  #29 = Utf8               LocalVariableTable
  #30 = Utf8               SourceFile
{
  public static void printString(java.lang.String);
    descriptor: (Ljava/lang/String;)V
    flags: ACC_PUBLIC, ACC_STATIC
    Code:
      stack=2, locals=1, args_size=1
         0: getstatic     #13                 // Field java/lang/System.out:Ljava/io/PrintStream;
         3: aload_0
         4: invokevirtual #18                 // Method java/io/PrintStream.println:(Ljava/lang/String;)V
         7: return
      LocalVariableTable:
        Start  Length  Slot  Name   Signature
            0       8     0 string   Ljava/lang/String;

  public com.github.jonathanxd.codeapi.test.bytecode.CodeAPITest_API_Generated();
    descriptor: ()V
    flags: ACC_PUBLIC
    Code:
      stack=1, locals=1, args_size=1
         0: aload_0
         1: invokespecial #24                 // Method java/lang/Object."<init>":()V
         4: return
      LocalVariableTable:
        Start  Length  Slot  Name   Signature
            0       5     0  this   Lcom/github/jonathanxd/codeapi/test/bytecode/CodeAPITest_API_Generated;

  static {};
    descriptor: ()V
    flags: ACC_STATIC
    Code:
      stack=0, locals=0, args_size=0
         0: return
}
SourceFile: "CodeAPITest_API_Generated.cai"
