Classfile /home/jonathan/workspace/CodeAPI/src/test/resources/CodeAPITestBytecode_Result.class
  Last modified 06/12/2016; size 1371 bytes
  MD5 checksum c7e8d02efb88bbfa2127354dbdc09284
  Compiled from "CodeAPITestBytecode.cai"
public class github.com.CodeAPITestBytecode
  minor version: 0
  major version: 52
  flags: ACC_PUBLIC, ACC_SUPER
Constant pool:
   #1 = Utf8               CodeAPITestBytecode.cai
   #2 = Utf8               github/com/CodeAPITestBytecode
   #3 = Class              #2             // github/com/CodeAPITestBytecode
   #4 = Utf8               java/lang/Object
   #5 = Class              #4             // java/lang/Object
   #6 = Utf8               println
   #7 = Utf8               (Ljava/lang/Object;)V
   #8 = Utf8               com/github/jonathanxd/codeapi/test/bytecode/CodeAPITestBytecode
   #9 = Class              #8             // com/github/jonathanxd/codeapi/test/bytecode/CodeAPITestBytecode
  #10 = Utf8               <init>
  #11 = Utf8               ()V
  #12 = NameAndType        #10:#11        // "<init>":()V
  #13 = Methodref          #9.#12         // com/github/jonathanxd/codeapi/test/bytecode/CodeAPITestBytecode."<init>":()V
  #14 = Utf8               java/lang/System
  #15 = Class              #14            // java/lang/System
  #16 = Utf8               out
  #17 = Utf8               Ljava/io/PrintStream;
  #18 = NameAndType        #16:#17        // out:Ljava/io/PrintStream;
  #19 = Fieldref           #15.#18        // java/lang/System.out:Ljava/io/PrintStream;
  #20 = Utf8               b
  #21 = Utf8               Ljava/lang/String;
  #22 = NameAndType        #20:#21        // b:Ljava/lang/String;
  #23 = Fieldref           #9.#22         // com/github/jonathanxd/codeapi/test/bytecode/CodeAPITestBytecode.b:Ljava/lang/String;
  #24 = Utf8               java/io/PrintStream
  #25 = Class              #24            // java/io/PrintStream
  #26 = Utf8               (Ljava/lang/String;)V
  #27 = NameAndType        #6:#26         // println:(Ljava/lang/String;)V
  #28 = Methodref          #25.#27        // java/io/PrintStream.println:(Ljava/lang/String;)V
  #29 = Utf8               java/lang/IllegalArgumentException
  #30 = Class              #29            // java/lang/IllegalArgumentException
  #31 = Utf8               java/lang/IllegalStateException
  #32 = Class              #31            // java/lang/IllegalStateException
  #33 = Utf8               java/io/IOException
  #34 = Class              #33            // java/io/IOException
  #35 = Utf8               java/lang/ClassNotFoundException
  #36 = Class              #35            // java/lang/ClassNotFoundException
  #37 = NameAndType        #6:#7          // println:(Ljava/lang/Object;)V
  #38 = Methodref          #25.#37        // java/io/PrintStream.println:(Ljava/lang/Object;)V
  #39 = Utf8               Error
  #40 = String             #39            // Error
  #41 = NameAndType        #10:#26        // "<init>":(Ljava/lang/String;)V
  #42 = Methodref          #32.#41        // java/lang/IllegalStateException."<init>":(Ljava/lang/String;)V
  #43 = Utf8               Finally!
  #44 = String             #43            // Finally!
  #45 = Utf8               Rethrow from var 'thr'!
  #46 = String             #45            // Rethrow from var 'thr'!
  #47 = Utf8               java/lang/Throwable
  #48 = Class              #47            // java/lang/Throwable
  #49 = Utf8               printStackTrace
  #50 = NameAndType        #49:#11        // printStackTrace:()V
  #51 = Methodref          #48.#50        // java/lang/Throwable.printStackTrace:()V
  #52 = Utf8               Rethrow from var 'tlr'!
  #53 = String             #52            // Rethrow from var 'tlr'!
  #54 = Utf8               java/lang/RuntimeException
  #55 = Class              #54            // java/lang/RuntimeException
  #56 = Utf8               java/lang/Exception
  #57 = Class              #56            // java/lang/Exception
  #58 = Utf8               msg
  #59 = Utf8               Ljava/lang/Object;
  #60 = Utf8               test
  #61 = Utf8               Lcom/github/jonathanxd/codeapi/test/bytecode/CodeAPITestBytecode;
  #62 = Utf8               ref
  #63 = Utf8               tlr
  #64 = Utf8               Ljava/lang/Throwable;
  #65 = Methodref          #5.#12         // java/lang/Object."<init>":()V
  #66 = Utf8               this
  #67 = Utf8               Lgithub/com/CodeAPITestBytecode;
  #68 = Utf8               <clinit>
  #69 = Utf8               Code
  #70 = Utf8               LocalVariableTable
  #71 = Utf8               StackMapTable
  #72 = Utf8               SourceFile
{
  public static void println(java.lang.Object);
    descriptor: (Ljava/lang/Object;)V
    flags: ACC_PUBLIC, ACC_STATIC
    Code:
      stack=3, locals=4, args_size=1
         0: new           #9                  // class com/github/jonathanxd/codeapi/test/bytecode/CodeAPITestBytecode
         3: dup
         4: invokespecial #13                 // Method com/github/jonathanxd/codeapi/test/bytecode/CodeAPITestBytecode."<init>":()V
         7: astore_1
         8: getstatic     #19                 // Field java/lang/System.out:Ljava/io/PrintStream;
        11: aload_1
        12: getfield      #23                 // Field com/github/jonathanxd/codeapi/test/bytecode/CodeAPITestBytecode.b:Ljava/lang/String;
        15: invokevirtual #28                 // Method java/io/PrintStream.println:(Ljava/lang/String;)V
        18: aload_0
        19: ifnull        29
        22: getstatic     #19                 // Field java/lang/System.out:Ljava/io/PrintStream;
        25: aload_0
        26: invokevirtual #38                 // Method java/io/PrintStream.println:(Ljava/lang/Object;)V
        29: getstatic     #19                 // Field java/lang/System.out:Ljava/io/PrintStream;
        32: astore_2
        33: new           #32                 // class java/lang/IllegalStateException
        36: dup
        37: ldc           #40                 // String Error
        39: invokespecial #42                 // Method java/lang/IllegalStateException."<init>":(Ljava/lang/String;)V
        42: athrow
        43: nop
        44: nop
        45: nop
        46: nop
        47: nop
        48: nop
        49: athrow
        50: nop
        51: nop
        52: nop
        53: nop
        54: nop
        55: nop
        56: nop
        57: nop
        58: nop
        59: nop
        60: athrow
        61: astore_3
        62: getstatic     #19                 // Field java/lang/System.out:Ljava/io/PrintStream;
        65: ldc           #46                 // String Rethrow from var 'thr'!
        67: invokevirtual #28                 // Method java/io/PrintStream.println:(Ljava/lang/String;)V
        70: aload_3
        71: invokevirtual #51                 // Method java/lang/Throwable.printStackTrace:()V
        74: getstatic     #19                 // Field java/lang/System.out:Ljava/io/PrintStream;
        77: ldc           #44                 // String Finally!
        79: invokevirtual #28                 // Method java/io/PrintStream.println:(Ljava/lang/String;)V
        82: goto          109
        85: astore_3
        86: getstatic     #19                 // Field java/lang/System.out:Ljava/io/PrintStream;
        89: ldc           #53                 // String Rethrow from var 'tlr'!
        91: invokevirtual #28                 // Method java/io/PrintStream.println:(Ljava/lang/String;)V
        94: aload_3
        95: invokevirtual #51                 // Method java/lang/Throwable.printStackTrace:()V
        98: getstatic     #19                 // Field java/lang/System.out:Ljava/io/PrintStream;
       101: ldc           #44                 // String Finally!
       103: invokevirtual #28                 // Method java/io/PrintStream.println:(Ljava/lang/String;)V
       106: goto          109
       109: return
      Exception table:
         from    to  target type
            18    43    61   Class java/lang/IllegalArgumentException
            18    43    61   Class java/lang/IllegalStateException
            18    43    85   Class java/io/IOException
            18    43    85   Class java/lang/ClassNotFoundException
      LocalVariableTable:
        Start  Length  Slot  Name   Signature
            0     110     0   msg   Ljava/lang/Object;
            7     103     1  test   Lcom/github/jonathanxd/codeapi/test/bytecode/CodeAPITestBytecode;
           32      78     2   ref   Ljava/lang/Object;
           85      24     3   tlr   Ljava/lang/Throwable;
      StackMapTable: number_of_entries = 6
        frame_type = 252 /* append */
          offset_delta = 29
          locals = [ class com/github/jonathanxd/codeapi/test/bytecode/CodeAPITestBytecode ]
        frame_type = 255 /* full_frame */
          offset_delta = 13
          locals = []
          stack = [ class java/lang/Throwable ]
        frame_type = 70 /* same_locals_1_stack_item */
          stack = [ class java/lang/Throwable ]
        frame_type = 255 /* full_frame */
          offset_delta = 10
          locals = [ class java/lang/Object, class com/github/jonathanxd/codeapi/test/bytecode/CodeAPITestBytecode ]
          stack = [ class java/lang/RuntimeException ]
        frame_type = 87 /* same_locals_1_stack_item */
          stack = [ class java/lang/Exception ]
        frame_type = 253 /* append */
          offset_delta = 23
          locals = [ top, class java/lang/Exception ]

  public github.com.CodeAPITestBytecode();
    descriptor: ()V
    flags: ACC_PUBLIC
    Code:
      stack=1, locals=1, args_size=1
         0: aload_0
         1: invokespecial #65                 // Method java/lang/Object."<init>":()V
         4: return
      LocalVariableTable:
        Start  Length  Slot  Name   Signature
            0       5     0  this   Lgithub/com/CodeAPITestBytecode;

  static {};
    descriptor: ()V
    flags: ACC_STATIC
    Code:
      stack=0, locals=0, args_size=0
         0: return
}
SourceFile: "CodeAPITestBytecode.cai"
