Classfile /home/jonathan/workspace/CodeAPI/src/test/resources/ConcatTest_ConcatTest_Result.class
  Last modified 06/12/2016; size 792 bytes
  MD5 checksum e90ea951871d084644adff173c606673
  Compiled from "ConcatTest.cai"
public class com.ConcatTest
  minor version: 0
  major version: 52
  flags: ACC_PUBLIC, ACC_SUPER
Constant pool:
   #1 = Utf8               ConcatTest.cai
   #2 = Utf8               com/ConcatTest
   #3 = Class              #2             // com/ConcatTest
   #4 = Utf8               java/lang/Object
   #5 = Class              #4             // java/lang/Object
   #6 = Utf8               <init>
   #7 = Utf8               (Ljava/lang/String;)V
   #8 = Utf8               ()V
   #9 = NameAndType        #6:#8          // "<init>":()V
  #10 = Methodref          #5.#9          // java/lang/Object."<init>":()V
  #11 = Utf8               java/lang/System
  #12 = Class              #11            // java/lang/System
  #13 = Utf8               out
  #14 = Utf8               Ljava/io/PrintStream;
  #15 = NameAndType        #13:#14        // out:Ljava/io/PrintStream;
  #16 = Fieldref           #12.#15        // java/lang/System.out:Ljava/io/PrintStream;
  #17 = Utf8               java/lang/StringBuilder
  #18 = Class              #17            // java/lang/StringBuilder
  #19 = Utf8               Hello
  #20 = String             #19            // Hello
  #21 = NameAndType        #6:#7          // "<init>":(Ljava/lang/String;)V
  #22 = Methodref          #18.#21        // java/lang/StringBuilder."<init>":(Ljava/lang/String;)V
  #23 = Utf8
  #24 = String             #23            //
  #25 = Utf8               append
  #26 = Utf8               (Ljava/lang/String;)Ljava/lang/StringBuilder;
  #27 = NameAndType        #25:#26        // append:(Ljava/lang/String;)Ljava/lang/StringBuilder;
  #28 = Methodref          #18.#27        // java/lang/StringBuilder.append:(Ljava/lang/String;)Ljava/lang/StringBuilder;
  #29 = Utf8                :D
  #30 = String             #29            //  :D
  #31 = Utf8               toString
  #32 = Utf8               ()Ljava/lang/String;
  #33 = NameAndType        #31:#32        // toString:()Ljava/lang/String;
  #34 = Methodref          #5.#33         // java/lang/Object.toString:()Ljava/lang/String;
  #35 = Utf8               java/io/PrintStream
  #36 = Class              #35            // java/io/PrintStream
  #37 = Utf8               println
  #38 = NameAndType        #37:#7         // println:(Ljava/lang/String;)V
  #39 = Methodref          #36.#38        // java/io/PrintStream.println:(Ljava/lang/String;)V
  #40 = Utf8
  #41 = String             #40            //
  #42 = Utf8               A
  #43 = String             #42            // A
  #44 = Utf8               B
  #45 = String             #44            // B
  #46 = Utf8               java/lang/String
  #47 = Class              #46            // java/lang/String
  #48 = Utf8               concat
  #49 = Utf8               (Ljava/lang/String;)Ljava/lang/String;
  #50 = NameAndType        #48:#49        // concat:(Ljava/lang/String;)Ljava/lang/String;
  #51 = Methodref          #47.#50        // java/lang/String.concat:(Ljava/lang/String;)Ljava/lang/String;
  #52 = Utf8               this
  #53 = Utf8               Lcom/ConcatTest;
  #54 = Utf8               av
  #55 = Utf8               Ljava/lang/String;
  #56 = Utf8               <clinit>
  #57 = Utf8               Code
  #58 = Utf8               LocalVariableTable
  #59 = Utf8               SourceFile
{
  public com.ConcatTest(java.lang.String);
    descriptor: (Ljava/lang/String;)V
    flags: ACC_PUBLIC
    Code:
      stack=4, locals=2, args_size=2
         0: aload_0
         1: invokespecial #10                 // Method java/lang/Object."<init>":()V
         4: getstatic     #16                 // Field java/lang/System.out:Ljava/io/PrintStream;
         7: new           #18                 // class java/lang/StringBuilder
        10: dup
        11: ldc           #20                 // String Hello
        13: invokespecial #22                 // Method java/lang/StringBuilder."<init>":(Ljava/lang/String;)V
        16: ldc           #24                 // String
        18: invokevirtual #28                 // Method java/lang/StringBuilder.append:(Ljava/lang/String;)Ljava/lang/StringBuilder;
        21: aload_1
        22: invokevirtual #28                 // Method java/lang/StringBuilder.append:(Ljava/lang/String;)Ljava/lang/StringBuilder;
        25: ldc           #30                 // String  :D
        27: invokevirtual #28                 // Method java/lang/StringBuilder.append:(Ljava/lang/String;)Ljava/lang/StringBuilder;
        30: invokevirtual #34                 // Method java/lang/Object.toString:()Ljava/lang/String;
        33: invokevirtual #39                 // Method java/io/PrintStream.println:(Ljava/lang/String;)V
        36: getstatic     #16                 // Field java/lang/System.out:Ljava/io/PrintStream;
        39: ldc           #41                 // String
        41: invokevirtual #39                 // Method java/io/PrintStream.println:(Ljava/lang/String;)V
        44: getstatic     #16                 // Field java/lang/System.out:Ljava/io/PrintStream;
        47: ldc           #43                 // String A
        49: invokevirtual #39                 // Method java/io/PrintStream.println:(Ljava/lang/String;)V
        52: getstatic     #16                 // Field java/lang/System.out:Ljava/io/PrintStream;
        55: ldc           #43                 // String A
        57: ldc           #45                 // String B
        59: invokevirtual #51                 // Method java/lang/String.concat:(Ljava/lang/String;)Ljava/lang/String;
        62: invokevirtual #39                 // Method java/io/PrintStream.println:(Ljava/lang/String;)V
        65: return
      LocalVariableTable:
        Start  Length  Slot  Name   Signature
            0      66     0  this   Lcom/ConcatTest;
            0      66     1    av   Ljava/lang/String;

  static {};
    descriptor: ()V
    flags: ACC_STATIC
    Code:
      stack=0, locals=0, args_size=0
         0: return
}
SourceFile: "ConcatTest.cai"
