Classfile /home/jonathan/workspace/CodeAPI/src/test/resources/EnumTest_MyEnum_Result.class
  Last modified 17/11/2016; size 1012 bytes
  MD5 checksum 5975822f6cb357de0b642052eebcbc25
  Compiled from "MyEnum.cai"
public abstract class com.MyEnum extends java.lang.Enum<com.MyEnum>
  minor version: 0
  major version: 52
  flags: ACC_PUBLIC, ACC_SUPER, ACC_ABSTRACT, ACC_ENUM
Constant pool:
   #1 = Utf8               MyEnum.cai
   #2 = Utf8               com/MyEnum
   #3 = Class              #2             // com/MyEnum
   #4 = Utf8               Ljava/lang/Enum<Lcom/MyEnum;>;
   #5 = Utf8               java/lang/Enum
   #6 = Class              #5             // java/lang/Enum
   #7 = Utf8               com/github/jonathanxd/codeapi/test/EnumTest_$MyItf
   #8 = Class              #7             // com/github/jonathanxd/codeapi/test/EnumTest_$MyItf
   #9 = Utf8               com/MyEnum$A$Inner
  #10 = Class              #9             // com/MyEnum$A$Inner
  #11 = Utf8               com.MyEnum$A$Inner
  #12 = Utf8               com/MyEnum$B$Inner
  #13 = Class              #12            // com/MyEnum$B$Inner
  #14 = Utf8               com.MyEnum$B$Inner
  #15 = Utf8               A
  #16 = Utf8               Lcom/MyEnum;
  #17 = Utf8               B
  #18 = Utf8               $VALUES
  #19 = Utf8               [Lcom/MyEnum;
  #20 = Utf8               <init>
  #21 = Utf8               (Ljava/lang/String;I)V
  #22 = Utf8               ()V
  #23 = NameAndType        #20:#22        // "<init>":()V
  #24 = Methodref          #6.#23         // java/lang/Enum."<init>":()V
  #25 = NameAndType        #20:#21        // "<init>":(Ljava/lang/String;I)V
  #26 = Methodref          #3.#25         // com/MyEnum."<init>":(Ljava/lang/String;I)V
  #27 = Utf8               this
  #28 = Utf8               name
  #29 = Utf8               Ljava/lang/String;
  #30 = Utf8               ordinal
  #31 = Utf8               I
  #32 = Utf8               values
  #33 = Utf8               ()[Lcom/MyEnum;
  #34 = NameAndType        #18:#19        // $VALUES:[Lcom/MyEnum;
  #35 = Fieldref           #3.#34         // com/MyEnum.$VALUES:[Lcom/MyEnum;
  #36 = Class              #19            // "[Lcom/MyEnum;"
  #37 = Utf8               clone
  #38 = Utf8               ()Ljava/lang/Object;
  #39 = NameAndType        #37:#38        // clone:()Ljava/lang/Object;
  #40 = Methodref          #36.#39        // "[Lcom/MyEnum;".clone:()Ljava/lang/Object;
  #41 = Utf8               valueOf
  #42 = Utf8               (Ljava/lang/String;)Lcom/MyEnum;
  #43 = Utf8               (Ljava/lang/Class;Ljava/lang/String;)Ljava/lang/Enum;
  #44 = NameAndType        #41:#43        // valueOf:(Ljava/lang/Class;Ljava/lang/String;)Ljava/lang/Enum;
  #45 = Methodref          #6.#44         // java/lang/Enum.valueOf:(Ljava/lang/Class;Ljava/lang/String;)Ljava/lang/Enum;
  #46 = Utf8               <clinit>
  #47 = String             #15            // A
  #48 = Methodref          #10.#25        // com/MyEnum$A$Inner."<init>":(Ljava/lang/String;I)V
  #49 = NameAndType        #15:#16        // A:Lcom/MyEnum;
  #50 = Fieldref           #3.#49         // com/MyEnum.A:Lcom/MyEnum;
  #51 = String             #17            // B
  #52 = Methodref          #13.#25        // com/MyEnum$B$Inner."<init>":(Ljava/lang/String;I)V
  #53 = NameAndType        #17:#16        // B:Lcom/MyEnum;
  #54 = Fieldref           #3.#53         // com/MyEnum.B:Lcom/MyEnum;
  #55 = Utf8               Code
  #56 = Utf8               LocalVariableTable
  #57 = Utf8               Signature
  #58 = Utf8               SourceFile
  #59 = Utf8               InnerClasses
{
  public static final com.MyEnum A;
    descriptor: Lcom/MyEnum;
    flags: ACC_PUBLIC, ACC_STATIC, ACC_FINAL, ACC_ENUM

  public static final com.MyEnum B;
    descriptor: Lcom/MyEnum;
    flags: ACC_PUBLIC, ACC_STATIC, ACC_FINAL, ACC_ENUM

  private static final com.MyEnum[] $VALUES;
    descriptor: [Lcom/MyEnum;
    flags: ACC_PRIVATE, ACC_STATIC, ACC_FINAL, ACC_SYNTHETIC

  protected com.MyEnum(java.lang.String, int);
    descriptor: (Ljava/lang/String;I)V
    flags: ACC_PROTECTED, ACC_SYNTHETIC
    Code:
      stack=3, locals=3, args_size=3
         0: aload_0
         1: invokespecial #24                 // Method java/lang/Enum."<init>":()V
         4: aload_0
         5: aload_1
         6: iload_2
         7: invokespecial #26                 // Method "<init>":(Ljava/lang/String;I)V
        10: return
      LocalVariableTable:
        Start  Length  Slot  Name   Signature
            0      11     0  this   Lcom/MyEnum;
            0      11     1  name   Ljava/lang/String;
            0      11     2 ordinal   I

  public static com.MyEnum[] values();
    descriptor: ()[Lcom/MyEnum;
    flags: ACC_PUBLIC, ACC_STATIC
    Code:
      stack=1, locals=0, args_size=0
         0: getstatic     #35                 // Field $VALUES:[Lcom/MyEnum;
         3: invokevirtual #40                 // Method "[Lcom/MyEnum;".clone:()Ljava/lang/Object;
         6: checkcast     #36                 // class "[Lcom/MyEnum;"
         9: areturn

  public static com.MyEnum valueOf(java.lang.String);
    descriptor: (Ljava/lang/String;)Lcom/MyEnum;
    flags: ACC_PUBLIC, ACC_STATIC
    Code:
      stack=2, locals=1, args_size=1
         0: ldc           #3                  // class com/MyEnum
         2: aload_0
         3: invokestatic  #45                 // Method java/lang/Enum.valueOf:(Ljava/lang/Class;Ljava/lang/String;)Ljava/lang/Enum;
         6: checkcast     #3                  // class com/MyEnum
         9: areturn
      LocalVariableTable:
        Start  Length  Slot  Name   Signature
            0      10     0  name   Ljava/lang/String;

  static {};
    descriptor: ()V
    flags: ACC_STATIC
    Code:
      stack=0, locals=0, args_size=0
         0: ldc           #47                 // String A
         2: iconst_0
         3: invokespecial #48                 // Method com/MyEnum$A$Inner."<init>":(Ljava/lang/String;I)V
         6: putstatic     #50                 // Field A:Lcom/MyEnum;
         9: ldc           #51                 // String B
        11: iconst_1
        12: invokespecial #52                 // Method com/MyEnum$B$Inner."<init>":(Ljava/lang/String;I)V
        15: putstatic     #54                 // Field B:Lcom/MyEnum;
        18: iconst_2
        19: anewarray     #3                  // class com/MyEnum
        22: dup
        23: iconst_0
        24: getstatic     #50                 // Field A:Lcom/MyEnum;
        27: aastore
        28: dup
        29: iconst_1
        30: getstatic     #54                 // Field B:Lcom/MyEnum;
        33: aastore
        34: putstatic     #35                 // Field $VALUES:[Lcom/MyEnum;
        37: return
}
Signature: #4                           // Ljava/lang/Enum<Lcom/MyEnum;>;
SourceFile: "MyEnum.cai"
InnerClasses:
     static #11= #10 of #3; //com.MyEnum$A$Inner=class com/MyEnum$A$Inner of class com/MyEnum
     static #14= #13 of #3; //com.MyEnum$B$Inner=class com/MyEnum$B$Inner of class com/MyEnum
