Classfile /home/jonathan/workspace/CodeAPI/src/test/resources/FinalFieldWithThis_Test_Result.class
  Last modified 18/11/2016; size 488 bytes
  MD5 checksum 06869f3a3aed2c863de35e86bbba9f58
  Compiled from "Test.cai"
public class finalfieldwiththis.Test extends com.github.jonathanxd.codeapi.test.bytecode.FinalFieldWithThis$TestBox
  minor version: 0
  major version: 52
  flags: ACC_PUBLIC, ACC_SUPER
Constant pool:
   #1 = Utf8               Test.cai
   #2 = Utf8               finalfieldwiththis/Test
   #3 = Class              #2             // finalfieldwiththis/Test
   #4 = Utf8               com/github/jonathanxd/codeapi/test/bytecode/FinalFieldWithThis$TestBox
   #5 = Class              #4             // com/github/jonathanxd/codeapi/test/bytecode/FinalFieldWithThis$TestBox
   #6 = Utf8               testField
   #7 = Utf8               Lcom/github/jonathanxd/codeapi/test/bytecode/FinalFieldWithThis$TestBox;
   #8 = Utf8               <init>
   #9 = Utf8               ()V
  #10 = Utf8               (Ljava/lang/Object;)V
  #11 = NameAndType        #8:#10         // "<init>":(Ljava/lang/Object;)V
  #12 = Methodref          #5.#11         // com/github/jonathanxd/codeapi/test/bytecode/FinalFieldWithThis$TestBox."<init>":(Ljava/lang/Object;)V
  #13 = NameAndType        #6:#7          // testField:Lcom/github/jonathanxd/codeapi/test/bytecode/FinalFieldWithThis$TestBox;
  #14 = Fieldref           #3.#13         // finalfieldwiththis/Test.testField:Lcom/github/jonathanxd/codeapi/test/bytecode/FinalFieldWithThis$TestBox;
  #15 = Utf8               this
  #16 = Utf8               Lfinalfieldwiththis/Test;
  #17 = Utf8               <clinit>
  #18 = Utf8               Code
  #19 = Utf8               LocalVariableTable
  #20 = Utf8               SourceFile
{
  private final com.github.jonathanxd.codeapi.test.bytecode.FinalFieldWithThis$TestBox testField;
    descriptor: Lcom/github/jonathanxd/codeapi/test/bytecode/FinalFieldWithThis$TestBox;
    flags: ACC_PRIVATE, ACC_FINAL

  public finalfieldwiththis.Test();
    descriptor: ()V
    flags: ACC_PUBLIC
    Code:
      stack=4, locals=1, args_size=1
         0: aload_0
         1: aconst_null
         2: invokespecial #12                 // Method com/github/jonathanxd/codeapi/test/bytecode/FinalFieldWithThis$TestBox."<init>":(Ljava/lang/Object;)V
         5: aload_0
         6: new           #5                  // class com/github/jonathanxd/codeapi/test/bytecode/FinalFieldWithThis$TestBox
         9: dup
        10: aload_0
        11: invokespecial #12                 // Method com/github/jonathanxd/codeapi/test/bytecode/FinalFieldWithThis$TestBox."<init>":(Ljava/lang/Object;)V
        14: putfield      #14                 // Field testField:Lcom/github/jonathanxd/codeapi/test/bytecode/FinalFieldWithThis$TestBox;
        17: return
      LocalVariableTable:
        Start  Length  Slot  Name   Signature
            0      18     0  this   Lfinalfieldwiththis/Test;

  static {};
    descriptor: ()V
    flags: ACC_STATIC
    Code:
      stack=0, locals=0, args_size=0
         0: return
}
SourceFile: "Test.cai"
