Classfile /home/jonathan/workspace/CodeAPI/src/test/resources/GenericInterfaceTest_Result.class
  Last modified 06/12/2016; size 350 bytes
  MD5 checksum fc67d659dbc79a971321c15f784fe390
  Compiled from "clv.cai"
public class clv extends java.lang.Object implements java.util.ArrayList<java.lang.String>
  minor version: 0
  major version: 52
  flags: ACC_PUBLIC, ACC_SUPER
Constant pool:
   #1 = Utf8               clv.cai
   #2 = Utf8               clv
   #3 = Class              #2             // clv
   #4 = Utf8               Ljava/lang/Object;Ljava/util/ArrayList<Ljava/lang/String;>;
   #5 = Utf8               java/lang/Object
   #6 = Class              #5             // java/lang/Object
   #7 = Utf8               java/util/ArrayList
   #8 = Class              #7             // java/util/ArrayList
   #9 = Utf8               <init>
  #10 = Utf8               ()V
  #11 = NameAndType        #9:#10         // "<init>":()V
  #12 = Methodref          #6.#11         // java/lang/Object."<init>":()V
  #13 = Utf8               this
  #14 = Utf8               Lclv;
  #15 = Utf8               <clinit>
  #16 = Utf8               Code
  #17 = Utf8               LocalVariableTable
  #18 = Utf8               Signature
  #19 = Utf8               SourceFile
{
  public clv();
    descriptor: ()V
    flags: ACC_PUBLIC
    Code:
      stack=1, locals=1, args_size=1
         0: aload_0
         1: invokespecial #12                 // Method java/lang/Object."<init>":()V
         4: return
      LocalVariableTable:
        Start  Length  Slot  Name   Signature
            0       5     0  this   Lclv;

  static {};
    descriptor: ()V
    flags: ACC_STATIC
    Code:
      stack=0, locals=0, args_size=0
         0: return
}
Signature: #4                           // Ljava/lang/Object;Ljava/util/ArrayList<Ljava/lang/String;>;
SourceFile: "clv.cai"
