Classfile /home/jonathan/workspace/CodeAPI/src/test/resources/SwitchTest_SwitchTestClass_Result.class
  Last modified 18/11/2016; size 1589 bytes
  MD5 checksum aee8371570303a4653895be001000cf1
  Compiled from "SwitchTestClass.cai"
public class com.SwitchTestClass
  minor version: 0
  major version: 52
  flags: ACC_PUBLIC, ACC_SUPER
Constant pool:
   #1 = Utf8               SwitchTestClass.cai
   #2 = Utf8               com/SwitchTestClass
   #3 = Class              #2             // com/SwitchTestClass
   #4 = Utf8               java/lang/Object
   #5 = Class              #4             // java/lang/Object
   #6 = Utf8               <init>
   #7 = Utf8               (IILcom/github/jonathanxd/codeapi/test/SwitchTest_$TestEnum;Ljava/lang/String;Ljava/lang/Object;)V
   #8 = Utf8               ()V
   #9 = NameAndType        #6:#8          // "<init>":()V
  #10 = Methodref          #5.#9          // java/lang/Object."<init>":()V
  #11 = Utf8               java/lang/System
  #12 = Class              #11            // java/lang/System
  #13 = Utf8               out
  #14 = Utf8               Ljava/io/PrintStream;
  #15 = NameAndType        #13:#14        // out:Ljava/io/PrintStream;
  #16 = Fieldref           #12.#15        // java/lang/System.out:Ljava/io/PrintStream;
  #17 = Utf8               1
  #18 = String             #17            // 1
  #19 = Utf8               java/io/PrintStream
  #20 = Class              #19            // java/io/PrintStream
  #21 = Utf8               println
  #22 = Utf8               (Ljava/lang/String;)V
  #23 = NameAndType        #21:#22        // println:(Ljava/lang/String;)V
  #24 = Methodref          #20.#23        // java/io/PrintStream.println:(Ljava/lang/String;)V
  #25 = Utf8               3
  #26 = String             #25            // 3
  #27 = Utf8               5
  #28 = String             #27            // 5
  #29 = Utf8               default
  #30 = String             #29            // default
  #31 = Utf8               10
  #32 = String             #31            // 10
  #33 = Utf8               100
  #34 = String             #33            // 100
  #35 = Utf8               java/lang/Enum
  #36 = Class              #35            // java/lang/Enum
  #37 = Utf8               ordinal
  #38 = Utf8               ()I
  #39 = NameAndType        #37:#38        // ordinal:()I
  #40 = Methodref          #36.#39        // java/lang/Enum.ordinal:()I
  #41 = Utf8               A
  #42 = String             #41            // A
  #43 = Utf8               B
  #44 = String             #43            // B
  #45 = Utf8               B or default
  #46 = String             #45            // B or default
  #47 = Utf8               hashCode
  #48 = NameAndType        #47:#38        // hashCode:()I
  #49 = Methodref          #5.#48         // java/lang/Object.hashCode:()I
  #50 = Utf8               AH
  #51 = String             #50            // AH
  #52 = Utf8               equals
  #53 = Utf8               (Ljava/lang/Object;)Z
  #54 = NameAndType        #52:#53        // equals:(Ljava/lang/Object;)Z
  #55 = Methodref          #5.#54         // java/lang/Object.equals:(Ljava/lang/Object;)Z
  #56 = Utf8               XM
  #57 = String             #56            // XM
  #58 = Utf8               AHEAD
  #59 = String             #58            // AHEAD
  #60 = Utf8               Zero
  #61 = String             #60            // Zero
  #62 = Utf8               com/github/jonathanxd/codeapi/test/SwitchTest_$TestEnum
  #63 = Class              #62            // com/github/jonathanxd/codeapi/test/SwitchTest_$TestEnum
  #64 = Utf8               java/lang/String
  #65 = Class              #64            // java/lang/String
  #66 = Utf8               this
  #67 = Utf8               Lcom/SwitchTestClass;
  #68 = Utf8               number
  #69 = Utf8               I
  #70 = Utf8               number2
  #71 = Utf8               testEnum
  #72 = Utf8               Lcom/github/jonathanxd/codeapi/test/SwitchTest_$TestEnum;
  #73 = Utf8               str
  #74 = Utf8               Ljava/lang/String;
  #75 = Utf8               o
  #76 = Utf8               Ljava/lang/Object;
  #77 = Utf8               <clinit>
  #78 = Utf8               Code
  #79 = Utf8               LocalVariableTable
  #80 = Utf8               StackMapTable
  #81 = Utf8               SourceFile
{
  public com.SwitchTestClass(int, int, com.github.jonathanxd.codeapi.test.SwitchTest_$TestEnum, java.lang.String, java.lang.Object);
    descriptor: (IILcom/github/jonathanxd/codeapi/test/SwitchTest_$TestEnum;Ljava/lang/String;Ljava/lang/Object;)V
    flags: ACC_PUBLIC
    Code:
      stack=2, locals=6, args_size=6
         0: aload_0
         1: invokespecial #10                 // Method java/lang/Object."<init>":()V
         4: iload_1
         5: tableswitch   { // 1 to 5
                       1: 40
                       2: 70
                       3: 51
                       4: 70
                       5: 59
                 default: 70
            }
        40: getstatic     #16                 // Field java/lang/System.out:Ljava/io/PrintStream;
        43: ldc           #18                 // String 1
        45: invokevirtual #24                 // Method java/io/PrintStream.println:(Ljava/lang/String;)V
        48: goto          78
        51: getstatic     #16                 // Field java/lang/System.out:Ljava/io/PrintStream;
        54: ldc           #26                 // String 3
        56: invokevirtual #24                 // Method java/io/PrintStream.println:(Ljava/lang/String;)V
        59: getstatic     #16                 // Field java/lang/System.out:Ljava/io/PrintStream;
        62: ldc           #28                 // String 5
        64: invokevirtual #24                 // Method java/io/PrintStream.println:(Ljava/lang/String;)V
        67: goto          78
        70: getstatic     #16                 // Field java/lang/System.out:Ljava/io/PrintStream;
        73: ldc           #30                 // String default
        75: invokevirtual #24                 // Method java/io/PrintStream.println:(Ljava/lang/String;)V
        78: iload_2
        79: lookupswitch  { // 3
                       1: 112
                      10: 123
                     100: 134
                 default: 145
            }
       112: getstatic     #16                 // Field java/lang/System.out:Ljava/io/PrintStream;
       115: ldc           #18                 // String 1
       117: invokevirtual #24                 // Method java/io/PrintStream.println:(Ljava/lang/String;)V
       120: goto          153
       123: getstatic     #16                 // Field java/lang/System.out:Ljava/io/PrintStream;
       126: ldc           #32                 // String 10
       128: invokevirtual #24                 // Method java/io/PrintStream.println:(Ljava/lang/String;)V
       131: goto          153
       134: getstatic     #16                 // Field java/lang/System.out:Ljava/io/PrintStream;
       137: ldc           #34                 // String 100
       139: invokevirtual #24                 // Method java/io/PrintStream.println:(Ljava/lang/String;)V
       142: goto          153
       145: getstatic     #16                 // Field java/lang/System.out:Ljava/io/PrintStream;
       148: ldc           #30                 // String default
       150: invokevirtual #24                 // Method java/io/PrintStream.println:(Ljava/lang/String;)V
       153: aload_3
       154: invokevirtual #40                 // Method java/lang/Enum.ordinal:()I
       157: tableswitch   { // 0 to 1
                       0: 180
                       1: 191
                 default: 199
            }
       180: getstatic     #16                 // Field java/lang/System.out:Ljava/io/PrintStream;
       183: ldc           #42                 // String A
       185: invokevirtual #24                 // Method java/io/PrintStream.println:(Ljava/lang/String;)V
       188: goto          207
       191: getstatic     #16                 // Field java/lang/System.out:Ljava/io/PrintStream;
       194: ldc           #44                 // String B
       196: invokevirtual #24                 // Method java/io/PrintStream.println:(Ljava/lang/String;)V
       199: getstatic     #16                 // Field java/lang/System.out:Ljava/io/PrintStream;
       202: ldc           #46                 // String B or default
       204: invokevirtual #24                 // Method java/io/PrintStream.println:(Ljava/lang/String;)V
       207: aload         4
       209: invokevirtual #49                 // Method java/lang/Object.hashCode:()I
       212: lookupswitch  { // 3
                    2087: 248
                    2805: 269
                62242209: 290
                 default: 311
            }
       248: aload         4
       250: ldc           #51                 // String AH
       252: invokevirtual #55                 // Method java/lang/Object.equals:(Ljava/lang/Object;)Z
       255: ifeq          311
       258: getstatic     #16                 // Field java/lang/System.out:Ljava/io/PrintStream;
       261: ldc           #51                 // String AH
       263: invokevirtual #24                 // Method java/io/PrintStream.println:(Ljava/lang/String;)V
       266: goto          319
       269: aload         4
       271: ldc           #57                 // String XM
       273: invokevirtual #55                 // Method java/lang/Object.equals:(Ljava/lang/Object;)Z
       276: ifeq          311
       279: getstatic     #16                 // Field java/lang/System.out:Ljava/io/PrintStream;
       282: ldc           #57                 // String XM
       284: invokevirtual #24                 // Method java/io/PrintStream.println:(Ljava/lang/String;)V
       287: goto          319
       290: aload         4
       292: ldc           #59                 // String AHEAD
       294: invokevirtual #55                 // Method java/lang/Object.equals:(Ljava/lang/Object;)Z
       297: ifeq          311
       300: getstatic     #16                 // Field java/lang/System.out:Ljava/io/PrintStream;
       303: ldc           #59                 // String AHEAD
       305: invokevirtual #24                 // Method java/io/PrintStream.println:(Ljava/lang/String;)V
       308: goto          319
       311: getstatic     #16                 // Field java/lang/System.out:Ljava/io/PrintStream;
       314: ldc           #30                 // String default
       316: invokevirtual #24                 // Method java/io/PrintStream.println:(Ljava/lang/String;)V
       319: aload         5
       321: invokevirtual #49                 // Method java/lang/Object.hashCode:()I
       324: lookupswitch  { // 1
                       0: 344
                 default: 355
            }
       344: getstatic     #16                 // Field java/lang/System.out:Ljava/io/PrintStream;
       347: ldc           #61                 // String Zero
       349: invokevirtual #24                 // Method java/io/PrintStream.println:(Ljava/lang/String;)V
       352: goto          363
       355: getstatic     #16                 // Field java/lang/System.out:Ljava/io/PrintStream;
       358: ldc           #30                 // String default
       360: invokevirtual #24                 // Method java/io/PrintStream.println:(Ljava/lang/String;)V
       363: return
      LocalVariableTable:
        Start  Length  Slot  Name   Signature
            0     364     0  this   Lcom/SwitchTestClass;
            0     364     1 number   I
            0     364     2 number2   I
            0     364     3 testEnum   Lcom/github/jonathanxd/codeapi/test/SwitchTest_$TestEnum;
            0     364     4   str   Ljava/lang/String;
            0     364     5     o   Ljava/lang/Object;
      StackMapTable: number_of_entries = 22
        frame_type = 255 /* full_frame */
          offset_delta = 40
          locals = [ class com/SwitchTestClass, int, int, class com/github/jonathanxd/codeapi/test/SwitchTest_$TestEnum, class java/lang/String, class java/lang/Object ]
          stack = []
        frame_type = 10 /* same */
        frame_type = 7 /* same */
        frame_type = 10 /* same */
        frame_type = 7 /* same */
        frame_type = 33 /* same */
        frame_type = 10 /* same */
        frame_type = 10 /* same */
        frame_type = 10 /* same */
        frame_type = 7 /* same */
        frame_type = 26 /* same */
        frame_type = 10 /* same */
        frame_type = 7 /* same */
        frame_type = 7 /* same */
        frame_type = 40 /* same */
        frame_type = 20 /* same */
        frame_type = 20 /* same */
        frame_type = 20 /* same */
        frame_type = 7 /* same */
        frame_type = 24 /* same */
        frame_type = 10 /* same */
        frame_type = 7 /* same */

  static {};
    descriptor: ()V
    flags: ACC_STATIC
    Code:
      stack=0, locals=0, args_size=0
         0: return
}
SourceFile: "SwitchTestClass.cai"
