Classfile /home/jonathan/workspace/CodeAPI/src/test/resources/TestRead_Generic_Result.class
  Last modified 19/11/2016; size 669 bytes
  MD5 checksum e507592bd4d18e52ca60a3b58851d3e7
  Compiled from "Generic.cai"
public class com.Generic<T extends java.util.List<T>> extends java.lang.Object implements java.util.List<T>
  minor version: 0
  major version: 52
  flags: ACC_PUBLIC, ACC_SUPER
Constant pool:
   #1 = Utf8               Generic.cai
   #2 = Utf8               com/Generic
   #3 = Class              #2             // com/Generic
   #4 = Utf8               <T::Ljava/util/List<TT;>;>Ljava/lang/Object;Ljava/util/List<TT;>;
   #5 = Utf8               java/lang/Object
   #6 = Class              #5             // java/lang/Object
   #7 = Utf8               java/util/List
   #8 = Class              #7             // java/util/List
   #9 = Utf8               test
  #10 = Utf8               (Ljava/lang/Object;)V
  #11 = Utf8               java/lang/Throwable
  #12 = Class              #11            // java/lang/Throwable
  #13 = Utf8               val
  #14 = Utf8               TT;
  #15 = Utf8               Ljava/lang/Object;
  #16 = Utf8               fieldi
  #17 = Utf8               <init>
  #18 = Utf8               ()V
  #19 = NameAndType        #17:#18        // "<init>":()V
  #20 = Methodref          #6.#19         // java/lang/Object."<init>":()V
  #21 = Utf8               this
  #22 = Utf8               Lcom/Generic;
  #23 = Utf8               <clinit>
  #24 = Utf8               Signature
  #25 = Utf8               Code
  #26 = Utf8               LocalVariableTable
  #27 = Utf8               LocalVariableTypeTable
  #28 = Utf8               StackMapTable
  #29 = Utf8               (TT;)V
  #30 = Utf8               SourceFile
{
  public T test;
    descriptor: Ljava/lang/Object;
    flags: ACC_PUBLIC
    Signature: #14                          // TT;

  public static void test(T);
    descriptor: (Ljava/lang/Object;)V
    flags: ACC_PUBLIC, ACC_STATIC
    Code:
      stack=1, locals=2, args_size=1
         0: aconst_null
         1: astore_1
         2: return
         3: athrow
      LocalVariableTable:
        Start  Length  Slot  Name   Signature
            0       4     0   val   Ljava/lang/Object;
            1       3     1 fieldi   Ljava/lang/Object;
      LocalVariableTypeTable:
        Start  Length  Slot  Name   Signature
            0       4     0   val   TT;
            1       3     1 fieldi   TT;
      StackMapTable: number_of_entries = 1
        frame_type = 255 /* full_frame */
          offset_delta = 3
          locals = []
          stack = [ class java/lang/Throwable ]
    Signature: #29                          // (TT;)V

  public com.Generic();
    descriptor: ()V
    flags: ACC_PUBLIC
    Code:
      stack=1, locals=1, args_size=1
         0: aload_0
         1: invokespecial #20                 // Method java/lang/Object."<init>":()V
         4: return
         5: athrow
      LocalVariableTable:
        Start  Length  Slot  Name   Signature
            0       6     0  this   Lcom/Generic;
      StackMapTable: number_of_entries = 1
        frame_type = 255 /* full_frame */
          offset_delta = 5
          locals = []
          stack = [ class java/lang/Throwable ]

  static {};
    descriptor: ()V
    flags: ACC_STATIC
    Code:
      stack=0, locals=0, args_size=0
         0: return
}
Signature: #4                           // <T::Ljava/util/List<TT;>;>Ljava/lang/Object;Ljava/util/List<TT;>;
SourceFile: "Generic.cai"
