Classfile /home/jonathan/workspace/CodeAPI/src/test/resources/TestLoopBytecode_Result.class
  Last modified 17/11/2016; size 647 bytes
  MD5 checksum 30490a0230ddf7635e617473ff116a21
  Compiled from "TestLoopBytecode.cai"
public class fullName.TestLoopBytecode
  minor version: 0
  major version: 52
  flags: ACC_PUBLIC, ACC_SUPER
Constant pool:
   #1 = Utf8               TestLoopBytecode.cai
   #2 = Utf8               fullName/TestLoopBytecode
   #3 = Class              #2             // fullName/TestLoopBytecode
   #4 = Utf8               java/lang/Object
   #5 = Class              #4             // java/lang/Object
   #6 = Utf8               <init>
   #7 = Utf8               ()V
   #8 = NameAndType        #6:#7          // "<init>":()V
   #9 = Methodref          #5.#8          // java/lang/Object."<init>":()V
  #10 = Utf8               java/lang/System
  #11 = Class              #10            // java/lang/System
  #12 = Utf8               out
  #13 = Utf8               Ljava/io/PrintStream;
  #14 = NameAndType        #12:#13        // out:Ljava/io/PrintStream;
  #15 = Fieldref           #11.#14        // java/lang/System.out:Ljava/io/PrintStream;
  #16 = Utf8               java/io/PrintStream
  #17 = Class              #16            // java/io/PrintStream
  #18 = Utf8               println
  #19 = Utf8               (I)V
  #20 = NameAndType        #18:#19        // println:(I)V
  #21 = Methodref          #17.#20        // java/io/PrintStream.println:(I)V
  #22 = Utf8               Hello World
  #23 = String             #22            // Hello World
  #24 = Utf8               (Ljava/lang/String;)V
  #25 = NameAndType        #18:#24        // println:(Ljava/lang/String;)V
  #26 = Methodref          #17.#25        // java/io/PrintStream.println:(Ljava/lang/String;)V
  #27 = Utf8               this
  #28 = Utf8               LfullName/TestLoopBytecode;
  #29 = Utf8               x
  #30 = Utf8               I
  #31 = Utf8               i
  #32 = Utf8               u
  #33 = Utf8               <clinit>
  #34 = Utf8               Code
  #35 = Utf8               LocalVariableTable
  #36 = Utf8               StackMapTable
  #37 = Utf8               SourceFile
{
  public fullName.TestLoopBytecode();
    descriptor: ()V
    flags: ACC_PUBLIC
    Code:
      stack=2, locals=4, args_size=1
         0: aload_0
         1: invokespecial #9                  // Method java/lang/Object."<init>":()V
         4: iconst_0
         5: istore_1
         6: iload_1
         7: bipush        17
         9: if_icmpge     25
        12: getstatic     #15                 // Field java/lang/System.out:Ljava/io/PrintStream;
        15: iload_1
        16: invokevirtual #21                 // Method java/io/PrintStream.println:(I)V
        19: iinc          1, 1
        22: goto          6
        25: iconst_0
        26: istore_2
        27: iload_2
        28: bipush        100
        30: if_icmpge     54
        33: iload_2
        34: iconst_5
        35: if_icmpne     41
        38: goto          48
        41: getstatic     #15                 // Field java/lang/System.out:Ljava/io/PrintStream;
        44: iload_2
        45: invokevirtual #21                 // Method java/io/PrintStream.println:(I)V
        48: iinc          2, 1
        51: goto          27
        54: iconst_0
        55: istore_3
        56: iload_3
        57: iconst_5
        58: if_icmpge     61
        61: getstatic     #15                 // Field java/lang/System.out:Ljava/io/PrintStream;
        64: iload_3
        65: invokevirtual #21                 // Method java/io/PrintStream.println:(I)V
        68: iinc          3, 1
        71: iload_3
        72: iconst_2
        73: if_icmpne     79
        76: goto          84
        79: iload_3
        80: iconst_5
        81: if_icmplt     56
        84: getstatic     #15                 // Field java/lang/System.out:Ljava/io/PrintStream;
        87: ldc           #23                 // String Hello World
        89: invokevirtual #26                 // Method java/io/PrintStream.println:(Ljava/lang/String;)V
        92: return
      LocalVariableTable:
        Start  Length  Slot  Name   Signature
            0      93     0  this   LfullName/TestLoopBytecode;
            5      88     1     x   I
           26      67     2     i   I
           55      38     3     u   I
      StackMapTable: number_of_entries = 10
        frame_type = 255 /* full_frame */
          offset_delta = 6
          locals = [ class fullName/TestLoopBytecode, int ]
          stack = []
        frame_type = 18 /* same */
        frame_type = 252 /* append */
          offset_delta = 1
          locals = [ int ]
        frame_type = 13 /* same */
        frame_type = 6 /* same */
        frame_type = 5 /* same */
        frame_type = 252 /* append */
          offset_delta = 1
          locals = [ int ]
        frame_type = 4 /* same */
        frame_type = 17 /* same */
        frame_type = 4 /* same */

  static {};
    descriptor: ()V
    flags: ACC_STATIC
    Code:
      stack=0, locals=0, args_size=0
         0: return
}
SourceFile: "TestLoopBytecode.cai"
