Classfile /home/jonathan/workspace/CodeAPI/src/test/resources/Transformer_Result.class
  Last modified 18/11/2016; size 2743 bytes
  MD5 checksum e2b144fdd79e85498fb82a10d99d1b91
  Compiled from "TestBytecode_Invocations_Generated.cai"
public class fullName.TestBytecode_Invocations_Generated
  minor version: 0
  major version: 52
  flags: ACC_PUBLIC, ACC_SUPER
Constant pool:
    #1 = Utf8               TestBytecode_Invocations_Generated.cai
    #2 = Utf8               fullName/TestBytecode_Invocations_Generated
    #3 = Class              #2            // fullName/TestBytecode_Invocations_Generated
    #4 = Utf8               java/lang/Object
    #5 = Class              #4            // java/lang/Object
    #6 = Utf8               FIELD
    #7 = Utf8               Ljava/lang/String;
    #8 = Utf8               n
    #9 = Utf8               I
   #10 = Utf8               <init>
   #11 = Utf8               ()V
   #12 = NameAndType        #10:#11       // "<init>":()V
   #13 = Methodref          #5.#12        // java/lang/Object."<init>":()V
   #14 = Utf8               AVD
   #15 = String             #14           // AVD
   #16 = NameAndType        #6:#7         // FIELD:Ljava/lang/String;
   #17 = Fieldref           #3.#16        // fullName/TestBytecode_Invocations_Generated.FIELD:Ljava/lang/String;
   #18 = NameAndType        #8:#9         // n:I
   #19 = Fieldref           #3.#18        // fullName/TestBytecode_Invocations_Generated.n:I
   #20 = Utf8               java/lang/System
   #21 = Class              #20           // java/lang/System
   #22 = Utf8               out
   #23 = Utf8               Ljava/io/PrintStream;
   #24 = NameAndType        #22:#23       // out:Ljava/io/PrintStream;
   #25 = Fieldref           #21.#24       // java/lang/System.out:Ljava/io/PrintStream;
   #26 = Utf8               Hello
   #27 = String             #26           // Hello
   #28 = Utf8               java/io/PrintStream
   #29 = Class              #28           // java/io/PrintStream
   #30 = Utf8               println
   #31 = Utf8               (Ljava/lang/String;)V
   #32 = NameAndType        #30:#31       // println:(Ljava/lang/String;)V
   #33 = Methodref          #29.#32       // java/io/PrintStream.println:(Ljava/lang/String;)V
   #34 = Utf8               Oi
   #35 = String             #34           // Oi
   #36 = Utf8               printIt
   #37 = Utf8               (Ljava/lang/Object;)V
   #38 = NameAndType        #36:#37       // printIt:(Ljava/lang/Object;)V
   #39 = Methodref          #3.#38        // fullName/TestBytecode_Invocations_Generated.printIt:(Ljava/lang/Object;)V
   #40 = Utf8               this
   #41 = Utf8               LfullName/TestBytecode_Invocations_Generated;
   #42 = Utf8               Hello :D
   #43 = String             #42           // Hello :D
   #44 = Utf8               DingDong
   #45 = String             #44           // DingDong
   #46 = NameAndType        #30:#37       // println:(Ljava/lang/Object;)V
   #47 = Methodref          #29.#46       // java/io/PrintStream.println:(Ljava/lang/Object;)V
   #48 = Utf8               Ljava/lang/Object;
   #49 = Utf8               dingdong
   #50 = Utf8               check
   #51 = Utf8               (I)Z
   #52 = Utf8               xy
   #53 = String             #52           // xy
   #54 = Utf8               yz
   #55 = String             #54           // yz
   #56 = Utf8               com/github/jonathanxd/codeapi/test/bytecode/TestBytecode_Invocations
   #57 = Class              #56           // com/github/jonathanxd/codeapi/test/bytecode/TestBytecode_Invocations
   #58 = Utf8               bmp
   #59 = Utf8               (Ljava/lang/String;Ljava/lang/String;)V
   #60 = NameAndType        #58:#59       // bmp:(Ljava/lang/String;Ljava/lang/String;)V
   #61 = Methodref          #57.#60       // com/github/jonathanxd/codeapi/test/bytecode/TestBytecode_Invocations.bmp:(Ljava/lang/String;Ljava/lang/String;)V
   #62 = Utf8               Invoke Interface ->
   #63 = String             #62           // Invoke Interface ->
   #64 = Utf8               com/github/jonathanxd/codeapi/test/WorldGreeter
   #65 = Class              #64           // com/github/jonathanxd/codeapi/test/WorldGreeter
   #66 = Methodref          #65.#12       // com/github/jonathanxd/codeapi/test/WorldGreeter."<init>":()V
   #67 = Utf8               com/github/jonathanxd/codeapi/test/Greeter
   #68 = Class              #67           // com/github/jonathanxd/codeapi/test/Greeter
   #69 = Utf8               hello
   #70 = Utf8               ()Ljava/lang/String;
   #71 = NameAndType        #69:#70       // hello:()Ljava/lang/String;
   #72 = InterfaceMethodref #68.#71       // com/github/jonathanxd/codeapi/test/Greeter.hello:()Ljava/lang/String;
   #73 = Utf8               Invoke Interface <-
   #74 = String             #73           // Invoke Interface <-
   #75 = Utf8               Invoke Dynamic ->
   #76 = String             #75           // Invoke Dynamic ->
   #77 = Utf8               java/lang/invoke/LambdaMetafactory
   #78 = Class              #77           // java/lang/invoke/LambdaMetafactory
   #79 = Utf8               metafactory
   #80 = Utf8               (Ljava/lang/invoke/MethodHandles$Lookup;Ljava/lang/String;Ljava/lang/invoke/MethodType;Ljava/lang/invoke/MethodType;Ljava/lang/invoke/MethodHandle;Ljava/lang/invoke/MethodType;)Ljava/lang/invoke/CallSite;
   #81 = NameAndType        #79:#80       // metafactory:(Ljava/lang/invoke/MethodHandles$Lookup;Ljava/lang/String;Ljava/lang/invoke/MethodType;Ljava/lang/invoke/MethodType;Ljava/lang/invoke/MethodHandle;Ljava/lang/invoke/MethodType;)Ljava/lang/invoke/CallSite;
   #82 = Methodref          #78.#81       // java/lang/invoke/LambdaMetafactory.metafactory:(Ljava/lang/invoke/MethodHandles$Lookup;Ljava/lang/String;Ljava/lang/invoke/MethodType;Ljava/lang/invoke/MethodType;Ljava/lang/invoke/MethodHandle;Ljava/lang/invoke/MethodType;)Ljava/lang/invoke/CallSite;
   #83 = MethodHandle       #6:#82        // invokestatic java/lang/invoke/LambdaMetafactory.metafactory:(Ljava/lang/invoke/MethodHandles$Lookup;Ljava/lang/String;Ljava/lang/invoke/MethodType;Ljava/lang/invoke/MethodType;Ljava/lang/invoke/MethodHandle;Ljava/lang/invoke/MethodType;)Ljava/lang/invoke/CallSite;
   #84 = Utf8               ()Ljava/lang/Object;
   #85 = MethodType         #84           //  ()Ljava/lang/Object;
   #86 = Utf8               TestBytecode_Invocations_Generated_fragment$_2083968260
   #87 = NameAndType        #86:#70       // TestBytecode_Invocations_Generated_fragment$_2083968260:()Ljava/lang/String;
   #88 = Methodref          #3.#87        // fullName/TestBytecode_Invocations_Generated.TestBytecode_Invocations_Generated_fragment$_2083968260:()Ljava/lang/String;
   #89 = MethodHandle       #6:#88        // invokestatic fullName/TestBytecode_Invocations_Generated.TestBytecode_Invocations_Generated_fragment$_2083968260:()Ljava/lang/String;
   #90 = MethodType         #70           //  ()Ljava/lang/String;
   #91 = Utf8               get
   #92 = Utf8               ()Ljava/util/function/Supplier;
   #93 = NameAndType        #91:#92       // get:()Ljava/util/function/Supplier;
   #94 = InvokeDynamic      #0:#93        // #0:get:()Ljava/util/function/Supplier;
   #95 = Utf8               java/util/function/Supplier
   #96 = Class              #95           // java/util/function/Supplier
   #97 = NameAndType        #91:#84       // get:()Ljava/lang/Object;
   #98 = InterfaceMethodref #96.#97       // java/util/function/Supplier.get:()Ljava/lang/Object;
   #99 = Utf8               java/lang/String
  #100 = Class              #99           // java/lang/String
  #101 = MethodHandle       #9:#72        // invokeinterface com/github/jonathanxd/codeapi/test/Greeter.hello:()Ljava/lang/String;
  #102 = Utf8               (Lcom/github/jonathanxd/codeapi/test/Greeter;)Ljava/util/function/Supplier;
  #103 = NameAndType        #91:#102      // get:(Lcom/github/jonathanxd/codeapi/test/Greeter;)Ljava/util/function/Supplier;
  #104 = InvokeDynamic      #1:#103       // #1:get:(Lcom/github/jonathanxd/codeapi/test/Greeter;)Ljava/util/function/Supplier;
  #105 = Utf8               Invoke Dynamic <-
  #106 = String             #105          // Invoke Dynamic <-
  #107 = Utf8               Invoke Dynamic Bootstrap ->
  #108 = String             #107          // Invoke Dynamic Bootstrap ->
  #109 = Utf8               World
  #110 = String             #109          // World
  #111 = Utf8               myBootstrap
  #112 = Utf8               (Ljava/lang/invoke/MethodHandles$Lookup;Ljava/lang/String;Ljava/lang/invoke/MethodType;)Ljava/lang/invoke/CallSite;
  #113 = NameAndType        #111:#112     // myBootstrap:(Ljava/lang/invoke/MethodHandles$Lookup;Ljava/lang/String;Ljava/lang/invoke/MethodType;)Ljava/lang/invoke/CallSite;
  #114 = Methodref          #57.#113      // com/github/jonathanxd/codeapi/test/bytecode/TestBytecode_Invocations.myBootstrap:(Ljava/lang/invoke/MethodHandles$Lookup;Ljava/lang/String;Ljava/lang/invoke/MethodType;)Ljava/lang/invoke/CallSite;
  #115 = MethodHandle       #6:#114       // invokestatic com/github/jonathanxd/codeapi/test/bytecode/TestBytecode_Invocations.myBootstrap:(Ljava/lang/invoke/MethodHandles$Lookup;Ljava/lang/String;Ljava/lang/invoke/MethodType;)Ljava/lang/invoke/CallSite;
  #116 = Utf8               helloWorld
  #117 = NameAndType        #116:#31      // helloWorld:(Ljava/lang/String;)V
  #118 = InvokeDynamic      #2:#117       // #2:helloWorld:(Ljava/lang/String;)V
  #119 = Utf8               Invoke Dynamic Bootstrap <-
  #120 = String             #119          // Invoke Dynamic Bootstrap <-
  #121 = Utf8               (I)V
  #122 = NameAndType        #30:#121      // println:(I)V
  #123 = Methodref          #29.#122      // java/io/PrintStream.println:(I)V
  #124 = Utf8               x
  #125 = Utf8               greeter
  #126 = Utf8               Lcom/github/jonathanxd/codeapi/test/Greeter;
  #127 = Utf8               greetingVar
  #128 = Utf8               supplier2
  #129 = Utf8               Ljava/util/function/Supplier;
  #130 = Utf8               supplier
  #131 = Utf8               str
  #132 = Utf8               BRB
  #133 = String             #132          // BRB
  #134 = Utf8               <clinit>
  #135 = Utf8               Code
  #136 = Utf8               LocalVariableTable
  #137 = Utf8               StackMapTable
  #138 = Utf8               LineNumberTable
  #139 = Utf8               BootstrapMethods
  #140 = Utf8               SourceFile
  #141 = Utf8               Inicializado!
  #142 = String             #141          // Inicializado!
  #143 = Utf8               XSD
  #144 = String             #143          // XSD
  #145 = Utf8               java/lang/Throwable
  #146 = Class              #145          // java/lang/Throwable
{
  public final java.lang.String FIELD;
    descriptor: Ljava/lang/String;
    flags: ACC_PUBLIC, ACC_FINAL

  public final int n;
    descriptor: I
    flags: ACC_PUBLIC, ACC_FINAL

  public fullName.TestBytecode_Invocations_Generated();
    descriptor: ()V
    flags: ACC_PUBLIC
    Code:
      stack=2, locals=1, args_size=1
         0: aload_0
         1: invokespecial #13                 // Method java/lang/Object."<init>":()V
         4: aload_0
         5: ldc           #15                 // String AVD
         7: putfield      #17                 // Field FIELD:Ljava/lang/String;
        10: aload_0
        11: bipush        15
        13: putfield      #19                 // Field n:I
        16: getstatic     #25                 // Field java/lang/System.out:Ljava/io/PrintStream;
        19: ldc           #27                 // String Hello
        21: invokevirtual #33                 // Method java/io/PrintStream.println:(Ljava/lang/String;)V
        24: aload_0
        25: ldc           #35                 // String Oi
        27: invokevirtual #39                 // Method printIt:(Ljava/lang/Object;)V
        30: getstatic     #25                 // Field java/lang/System.out:Ljava/io/PrintStream;
        33: ldc           #142                // String Inicializado!
        35: invokevirtual #33                 // Method java/io/PrintStream.println:(Ljava/lang/String;)V
        38: return
      LocalVariableTable:
        Start  Length  Slot  Name   Signature
            0      39     0  this   LfullName/TestBytecode_Invocations_Generated;

  public void printIt(java.lang.Object);
    descriptor: (Ljava/lang/Object;)V
    flags: ACC_PUBLIC
    Code:
      stack=2, locals=3, args_size=2
         0: aload_1
         1: ifnull        12
         4: getstatic     #25                 // Field java/lang/System.out:Ljava/io/PrintStream;
         7: ldc           #43                 // String Hello :D
         9: invokevirtual #33                 // Method java/io/PrintStream.println:(Ljava/lang/String;)V
        12: ldc           #45                 // String DingDong
        14: astore_2
        15: getstatic     #25                 // Field java/lang/System.out:Ljava/io/PrintStream;
        18: aload_2
        19: invokevirtual #33                 // Method java/io/PrintStream.println:(Ljava/lang/String;)V
        22: getstatic     #25                 // Field java/lang/System.out:Ljava/io/PrintStream;
        25: aload_1
        26: invokevirtual #47                 // Method java/io/PrintStream.println:(Ljava/lang/Object;)V
        29: return
      LocalVariableTable:
        Start  Length  Slot  Name   Signature
            0      30     0  this   LfullName/TestBytecode_Invocations_Generated;
            0      30     1     n   Ljava/lang/Object;
           14      16     2 dingdong   Ljava/lang/String;
      StackMapTable: number_of_entries = 1
        frame_type = 12 /* same */

  public boolean check(int);
    descriptor: (I)Z
    flags: ACC_PUBLIC
    Code:
      stack=2, locals=7, args_size=2
         0: ldc           #53                 // String xy
         2: ldc           #55                 // String yz
         4: invokestatic  #61                 // Method com/github/jonathanxd/codeapi/test/bytecode/TestBytecode_Invocations.bmp:(Ljava/lang/String;Ljava/lang/String;)V
         7: getstatic     #25                 // Field java/lang/System.out:Ljava/io/PrintStream;
        10: ldc           #63                 // String Invoke Interface ->
        12: invokevirtual #33                 // Method java/io/PrintStream.println:(Ljava/lang/String;)V
        15: new           #65                 // class com/github/jonathanxd/codeapi/test/WorldGreeter
        18: dup
        19: invokespecial #66                 // Method com/github/jonathanxd/codeapi/test/WorldGreeter."<init>":()V
        22: astore_2
        23: aload_2
        24: invokeinterface #72,  1           // InterfaceMethod com/github/jonathanxd/codeapi/test/Greeter.hello:()Ljava/lang/String;
        29: astore_3
        30: getstatic     #25                 // Field java/lang/System.out:Ljava/io/PrintStream;
        33: aload_3
        34: invokevirtual #33                 // Method java/io/PrintStream.println:(Ljava/lang/String;)V
        37: getstatic     #25                 // Field java/lang/System.out:Ljava/io/PrintStream;
        40: ldc           #74                 // String Invoke Interface <-
        42: invokevirtual #33                 // Method java/io/PrintStream.println:(Ljava/lang/String;)V
        45: getstatic     #25                 // Field java/lang/System.out:Ljava/io/PrintStream;
        48: ldc           #76                 // String Invoke Dynamic ->
        50: invokevirtual #33                 // Method java/io/PrintStream.println:(Ljava/lang/String;)V
        53: invokedynamic #94,  0             // InvokeDynamic #0:get:()Ljava/util/function/Supplier;
        58: astore        4
        60: getstatic     #25                 // Field java/lang/System.out:Ljava/io/PrintStream;
        63: aload         4
        65: invokeinterface #98,  1           // InterfaceMethod java/util/function/Supplier.get:()Ljava/lang/Object;
        70: checkcast     #100                // class java/lang/String
        73: invokevirtual #33                 // Method java/io/PrintStream.println:(Ljava/lang/String;)V
        76: aload_2
        77: invokedynamic #104,  0            // InvokeDynamic #1:get:(Lcom/github/jonathanxd/codeapi/test/Greeter;)Ljava/util/function/Supplier;
        82: astore        5
        84: aload         5
        86: invokeinterface #98,  1           // InterfaceMethod java/util/function/Supplier.get:()Ljava/lang/Object;
        91: checkcast     #100                // class java/lang/String
        94: astore        6
        96: getstatic     #25                 // Field java/lang/System.out:Ljava/io/PrintStream;
        99: aload         6
       101: invokevirtual #33                 // Method java/io/PrintStream.println:(Ljava/lang/String;)V
       104: getstatic     #25                 // Field java/lang/System.out:Ljava/io/PrintStream;
       107: ldc           #106                // String Invoke Dynamic <-
       109: invokevirtual #33                 // Method java/io/PrintStream.println:(Ljava/lang/String;)V
       112: getstatic     #25                 // Field java/lang/System.out:Ljava/io/PrintStream;
       115: ldc           #108                // String Invoke Dynamic Bootstrap ->
       117: invokevirtual #33                 // Method java/io/PrintStream.println:(Ljava/lang/String;)V
       120: ldc           #110                // String World
       122: invokedynamic #118,  0            // InvokeDynamic #2:helloWorld:(Ljava/lang/String;)V
       127: getstatic     #25                 // Field java/lang/System.out:Ljava/io/PrintStream;
       130: ldc           #120                // String Invoke Dynamic Bootstrap <-
       132: invokevirtual #33                 // Method java/io/PrintStream.println:(Ljava/lang/String;)V
       135: iload_1
       136: bipush        9
       138: if_icmpeq     147
       141: iload_1
       142: bipush        7
       144: if_icmpne     149
       147: iconst_0
       148: ireturn
       149: getstatic     #25                 // Field java/lang/System.out:Ljava/io/PrintStream;
       152: iload_1
       153: invokevirtual #123                // Method java/io/PrintStream.println:(I)V
       156: iconst_1
       157: ireturn
      LocalVariableTable:
        Start  Length  Slot  Name   Signature
            0     158     0  this   LfullName/TestBytecode_Invocations_Generated;
            0     158     1     x   I
           22     136     2 greeter   Lcom/github/jonathanxd/codeapi/test/Greeter;
           29     129     3 greetingVar   Ljava/lang/String;
           58     100     4 supplier2   Ljava/util/function/Supplier;
           82      76     5 supplier   Ljava/util/function/Supplier;
           94      64     6   str   Ljava/lang/String;
      LineNumberTable:
        line 0: 120
      StackMapTable: number_of_entries = 2
        frame_type = 255 /* full_frame */
          offset_delta = 147
          locals = [ class fullName/TestBytecode_Invocations_Generated, int, class com/github/jonathanxd/codeapi/test/WorldGreeter, class java/lang/String, class java/util/function/Supplier, class java/util/function/Supplier, class java/lang/String ]
          stack = []
        frame_type = 1 /* same */

  private static java.lang.String TestBytecode_Invocations_Generated_fragment$_2083968260();
    descriptor: ()Ljava/lang/String;
    flags: ACC_PRIVATE, ACC_STATIC
    Code:
      stack=1, locals=0, args_size=0
         0: ldc           #133                // String BRB
         2: pop
         3: ldc           #144                // String XSD
         5: areturn
         6: athrow
      StackMapTable: number_of_entries = 1
        frame_type = 70 /* same_locals_1_stack_item */
          stack = [ class java/lang/Throwable ]

  static {};
    descriptor: ()V
    flags: ACC_STATIC
    Code:
      stack=0, locals=0, args_size=0
         0: return
}
BootstrapMethods:
  0: #83 invokestatic java/lang/invoke/LambdaMetafactory.metafactory:(Ljava/lang/invoke/MethodHandles$Lookup;Ljava/lang/String;Ljava/lang/invoke/MethodType;Ljava/lang/invoke/MethodType;Ljava/lang/invoke/MethodHandle;Ljava/lang/invoke/MethodType;)Ljava/lang/invoke/CallSite;
    Method arguments:
      #85 ()Ljava/lang/Object;
      #89 invokestatic fullName/TestBytecode_Invocations_Generated.TestBytecode_Invocations_Generated_fragment$_2083968260:()Ljava/lang/String;
      #90 ()Ljava/lang/String;
  1: #83 invokestatic java/lang/invoke/LambdaMetafactory.metafactory:(Ljava/lang/invoke/MethodHandles$Lookup;Ljava/lang/String;Ljava/lang/invoke/MethodType;Ljava/lang/invoke/MethodType;Ljava/lang/invoke/MethodHandle;Ljava/lang/invoke/MethodType;)Ljava/lang/invoke/CallSite;
    Method arguments:
      #85 ()Ljava/lang/Object;
      #101 invokeinterface com/github/jonathanxd/codeapi/test/Greeter.hello:()Ljava/lang/String;
      #90 ()Ljava/lang/String;
  2: #115 invokestatic com/github/jonathanxd/codeapi/test/bytecode/TestBytecode_Invocations.myBootstrap:(Ljava/lang/invoke/MethodHandles$Lookup;Ljava/lang/String;Ljava/lang/invoke/MethodType;)Ljava/lang/invoke/CallSite;
    Method arguments:
SourceFile: "TestBytecode_Invocations_Generated.cai"
